sobol/__init__.py
sobol/sobol.py
sobol/sobol1111.tsv
SobolSequence-0.2.1.dist-info/LICENSE
SobolSequence-0.2.1.dist-info/METADATA
SobolSequence-0.2.1.dist-info/WHEEL
SobolSequence-0.2.1.dist-info/top_level.txt
SobolSequence-0.2.1.dist-info/RECORD
