Metadata-Version: 2.1
Name: SobolSequence
Version: 0.2.1
Summary: Sobol sequence generator
Home-page: https://github.com/DavidWalz/sobol
Author: David Walz
License: UNKNOWN
Platform: UNKNOWN
Classifier: Programming Language :: Python :: 3
Classifier: License :: OSI Approved :: MIT License
Classifier: Operating System :: OS Independent
Classifier: Development Status :: 7 - Inactive
Classifier: Topic :: Scientific/Engineering
Requires-Python: >=3.5
Requires-Dist: numpy
